algos/__init__.py
algos/linear_search.py
search_algos-0.1.dist-info/METADATA
search_algos-0.1.dist-info/WHEEL
search_algos-0.1.dist-info/top_level.txt
search_algos-0.1.dist-info/RECORD
