Metadata-Version: 2.1
Name: search-algos
Version: 0.1
Summary: A collection of searching algorithms for lists and dictionaries
Author: Arpan Adhikari
Author-email: codewitharpan@gmail.com
License: UNKNOWN
Platform: UNKNOWN
